{
    "cSpell.customDictionaries": {
        "project-words": {
            "name": "project-words",
            "path": "${workspaceRoot}/whitelist.txt",
            "description": "Words used in this project",
            "addWords": true
        },
        "opcodes": {
            "name": "opcodes",
            "path": "${workspaceRoot}/.wordlist_opcodes.txt",
            "description": "List of EVM opcodes",
            "addWords": true
        },
        "python_pytest": {
            "name": "python_pytest",
            "path": "${workspaceRoot}/.wordlist_python_pytest.txt",
            "description": "List of python and pytest related words",
            "addWords": true
        },
        "custom": true, // Enable the `custom` dictionary
        "internal-terms": false // Disable the `internal-terms` dictionary
    },
    "[python]": {
        "editor.rulers": [100],
        "editor.formatOnSave": true,
        "editor.defaultFormatter": "ms-python.black-formatter",
        "editor.codeActionsOnSave": {
            "source.organizeImports": true
        }
    },
    "python.analysis.autoFormatStrings": true,
    "python.linting.mypyEnabled": true,
    "python.linting.flake8Enabled": true,
    "python.testing.promptToConfigure": false,
    "python.testing.unittestEnabled": false,
    "python.testing.pytestEnabled": true,
    "python.testing.pytestArgs": [
        // To discover tests for an upcoming fork, use the `--until` argument as following.
        // "--until=Cancun",
        // Hopefully vscode-python will support multiple test framework environments sooon, see
        // https://github.com/microsoft/vscode-python/issues/12075
        // For now, to toggle between running "framework tests" and "filling tests" comment/
        // uncomment the relevant line below.
        "-c",
        // "pytest-framework.ini",
        "pytest.ini"
        // "-vv"
    ],
    "black-formatter.args": [
        "--line-length",
        "99"
    ]
}
